[
    {
        "name": "Configuration_Guide.txt",
        "id": "0"
    },
    {
        "name": "imu",
        "id": "1"
    },
    {
        "name": "kipro",
        "id": "2"
    },
    {
        "name": "kipro.py",
        "id": "3"
    },
    {
        "name": "livelinkface.py",
        "id": "4"
    },
    {
        "name": "mass_export.py",
        "id": "5"
    },
    {
        "name": "motionbuilder.py",
        "id": "6"
    },
    {
        "name": "MyTakeRecorderController.cpp",
        "id": "7"
    },
    {
        "name": "MyTakeRecorderController.h",
        "id": "8"
    },
    {
        "name": "ping.py",
        "id": "9"
    },
    {
        "name": "python-osc-master",
        "id": "10"
    },
    {
        "name": "qualisys",
        "id": "11"
    },
    {
        "name": "receiver.py",
        "id": "12"
    },
    {
        "name": "sender.py",
        "id": "13"
    },
    {
        "name": "test.py",
        "id": "14"
    },
    {
        "name": "TrackingDataRecorder.py",
        "id": "15"
    },
    {
        "name": "unreal.py",
        "id": "16"
    },
    {
        "name": "vicon",
        "id": "17"
    },
    {
        "name": "ZDTransformOffsetLogTool.py",
        "id": "18"
    }
]